{
  "$schema": "https://raw.githubusercontent.com/black-atom-industries/core/refs/heads/main/adapter.schema.json",
  "collections": {
    "stations": {
      "template": "./themes/stations/collection.template.json",
      "themes": [
        "black-atom-stations-engineering"
      ]
    },
    "crbn": {
      "template": "./themes/crbn/collection.template.json",
      "themes": [
        "black-atom-crbn-null"
      ]
    },
    "jpn": {
      "template": "./themes/jpn/collection.template.json",
      "themes": [
        "black-atom-jpn-koyo-yoru"
      ]
    },
    "terra": {
      "template": "./themes/terra/collection.template.json",
      "themes": [
        "black-atom-terra-spring-day"
      ]
    }
  },
  "enabled": false
}
